[
  {
    "id": "Event1",
    "data": "2023-01-01",
    "oraInizio": "09:00",
    "oraFine": "17:00",
    "nomeOrganizzatore": "PAC",
    "elencoInterventi": [
      {
        "titolo": "Intervento 1",
        "relatore": "Relatore 1",
        "descrizione": "Descrizione dell\u0027intervento 1"
      },
      {
        "titolo": "Intervento 2",
        "relatore": "Relatore 2",
        "descrizione": "Descrizione dell\u0027intervento 2"
      }
    ],
    "costoPartecipazione": 100.0
  },
  {
    "id": "Event2",
    "data": "2023-01-02",
    "oraInizio": "09:00",
    "oraFine": "17:00",
    "nomeOrganizzatore": "PAC",
    "elencoInterventi": [
      {
        "titolo": "Intervento 3",
        "relatore": "Relatore 3",
        "descrizione": "Descrizione dell\u0027intervento 3"
      },
      {
        "titolo": "Intervento 4",
        "relatore": "Relatore 4",
        "descrizione": "Descrizione dell\u0027intervento 4"
      }
    ],
    "costoPartecipazione": 150.0
  },
  {
    "id": "Event4",
    "elencoInterventi": [],
    "costoPartecipazione": 0.0
  },
  {
    "id": "Event4",
    "elencoInterventi": [],
    "costoPartecipazione": 0.0
  },
  {
    "id": "Event5",
    "elencoInterventi": [],
    "costoPartecipazione": 0.0
  },
  {
    "id": "Event5",
    "elencoInterventi": [],
    "costoPartecipazione": 0.0
  },
  {
    "id": "Event5",
    "elencoInterventi": [],
    "costoPartecipazione": 0.0
  },
  {
    "id": "Event5",
    "elencoInterventi": [],
    "costoPartecipazione": 0.0
  },
  {
    "id": "Event9",
    "elencoInterventi": [],
    "costoPartecipazione": 0.0
  },
  {
    "id": "Event9",
    "elencoInterventi": [],
    "costoPartecipazione": 0.0
  },
  {
    "id": "Event9",
    "elencoInterventi": [],
    "costoPartecipazione": 0.0
  },
  {
    "id": "Event9",
    "elencoInterventi": [],
    "costoPartecipazione": 0.0
  },
  {
    "id": "Event9",
    "elencoInterventi": [],
    "costoPartecipazione": 0.0
  },
  {
    "id": "Event9",
    "elencoInterventi": [],
    "costoPartecipazione": 0.0
  },
  {
    "id": "Event9",
    "elencoInterventi": [],
    "costoPartecipazione": 0.0
  },
  {
    "id": "Event9",
    "elencoInterventi": [],
    "costoPartecipazione": 0.0
  },
  {
    "id": "Event019",
    "elencoInterventi": [],
    "costoPartecipazione": 0.0
  },
  {
    "id": "Event019",
    "elencoInterventi": [],
    "costoPartecipazione": 0.0
  },
  {
    "id": "Event019",
    "elencoInterventi": [],
    "costoPartecipazione": 0.0
  },
  {
    "id": "Event019",
    "elencoInterventi": [],
    "costoPartecipazione": 0.0
  },
  {
    "id": "Event019",
    "elencoInterventi": [],
    "costoPartecipazione": 0.0
  },
  {
    "id": "Event019",
    "elencoInterventi": [],
    "costoPartecipazione": 0.0
  },
  {
    "id": "Event019",
    "elencoInterventi": [],
    "costoPartecipazione": 0.0
  },
  {
    "id": "Event019",
    "elencoInterventi": [],
    "costoPartecipazione": 0.0
  },
  {
    "id": "Event019",
    "elencoInterventi": [],
    "costoPartecipazione": 0.0
  },
  {
    "id": "Event019",
    "elencoInterventi": [],
    "costoPartecipazione": 0.0
  },
  {
    "id": "Event019",
    "elencoInterventi": [],
    "costoPartecipazione": 0.0
  },
  {
    "id": "Event019",
    "elencoInterventi": [],
    "costoPartecipazione": 0.0
  },
  {
    "id": "Event019",
    "elencoInterventi": [],
    "costoPartecipazione": 0.0
  },
  {
    "id": "Event019",
    "elencoInterventi": [],
    "costoPartecipazione": 0.0
  },
  {
    "id": "Event019",
    "elencoInterventi": [],
    "costoPartecipazione": 0.0
  },
  {
    "id": "Event019",
    "elencoInterventi": [],
    "costoPartecipazione": 0.0
  }
]
